jupy/__init__.py
jupy/cli.py
jupy_sdk-0.0.0.dist-info/METADATA
jupy_sdk-0.0.0.dist-info/WHEEL
jupy_sdk-0.0.0.dist-info/entry_points.txt
jupy_sdk-0.0.0.dist-info/RECORD
