Metadata-Version: 2.1
Name: jupy-sdk
Version: 0.0.0
Summary: The Python SDK for jupy.dev
Author: The Jupy Authors
Author-email: dev@jupy.dev
Requires-Python: >=3.8,<4.0
Classifier: Programming Language :: Python :: 3
Classifier: Programming Language :: Python :: 3.8
Classifier: Programming Language :: Python :: 3.9
Classifier: Programming Language :: Python :: 3.10
Classifier: Programming Language :: Python :: 3.11
Classifier: Programming Language :: Python :: 3.12
Requires-Dist: build (>=1.2.1,<2.0.0)
Requires-Dist: requests (>=2.32.3,<3.0.0)
